alienHTML/__init__.py
alienHTML/alienHTML.py
alienHTML/tests/__init__.py
alienHTML/tests/test_webpage.py
alienHTML-0.0.7.dist-info/LICENSE
alienHTML-0.0.7.dist-info/METADATA
alienHTML-0.0.7.dist-info/WHEEL
alienHTML-0.0.7.dist-info/top_level.txt
alienHTML-0.0.7.dist-info/RECORD
