Metadata-Version: 2.1
Name: alienHTML
Version: 0.0.7
Summary: Python package to help with HTML development.
Home-page: https://github.com/TomTheCodingGuy/alienHTML
Author: TomTheCodingGuy
Author-email: <tomb80940@gmail.com>
License: UNKNOWN
Keywords: python,html,alien,alienHTML
Platform: UNKNOWN
Classifier: Development Status :: 3 - Alpha
Classifier: Intended Audience :: Developers
Classifier: License :: OSI Approved :: MIT License
Classifier: Programming Language :: Python :: 3
Classifier: Operating System :: OS Independent
Requires-Python: >=3.7
